vllm_musa_platform/__init__.py
vllm_musa_platform/musa.py
vllm_musa_platform/patches/__init__.py
vllm_musa_platform/patches/vllm__attention__ops__triton_unified_attention.patch.py
vllm_musa_platform/patches/vllm__v1__worker__gpu_worker.patch.py
vllm_musa_platform/patches/vllm__worker__worker.patch.py
vllm_musa-0.1.1.dist-info/METADATA
vllm_musa-0.1.1.dist-info/WHEEL
vllm_musa-0.1.1.dist-info/entry_points.txt
vllm_musa-0.1.1.dist-info/top_level.txt
vllm_musa-0.1.1.dist-info/RECORD
