Metadata-Version: 2.4
Name: vllm-musa
Version: 0.1.1
Summary: vLLM platform plugin for Moore Threads MUSA GPUs
Author: vLLM Community
License-Expression: Apache-2.0
Project-URL: Homepage, https://github.com/vllm-project/vllm
Project-URL: Repository, https://github.com/vllm-project/vllm
Keywords: vllm,musa,moore-threads,llm,inference
Classifier: Development Status :: 3 - Alpha
Classifier: Intended Audience :: Developers
Classifier: Intended Audience :: Science/Research
Classifier: Operating System :: POSIX :: Linux
Classifier: Programming Language :: Python :: 3
Classifier: Programming Language :: Python :: 3.9
Classifier: Programming Language :: Python :: 3.10
Classifier: Programming Language :: Python :: 3.11
Classifier: Programming Language :: Python :: 3.12
Classifier: Topic :: Scientific/Engineering :: Artificial Intelligence
Requires-Python: >=3.9
Requires-Dist: vllm
Requires-Dist: torch==2.7.1
Requires-Dist: torchada>=0.1.9
Requires-Dist: mthreads-ml-py>=2.2.5
Provides-Extra: dev
Requires-Dist: pytest; extra == "dev"
Requires-Dist: pytest-asyncio; extra == "dev"
Requires-Dist: pytest-cov; extra == "dev"
Requires-Dist: ruff; extra == "dev"
Requires-Dist: mypy; extra == "dev"
Requires-Dist: isort; extra == "dev"
Requires-Dist: black; extra == "dev"
Requires-Dist: build; extra == "dev"
Requires-Dist: twine; extra == "dev"
